alertalot/__init__.py
alertalot/main.py
alertalot/actions/__init__.py
alertalot/actions/aws_test_action.py
alertalot/actions/create_alarms_action.py
alertalot/actions/show_alarms_template_action.py
alertalot/actions/show_target_action.py
alertalot/actions/show_variables_action.py
alertalot/actions/sub_actions/__init__.py
alertalot/actions/sub_actions/create_alarm_action.py
alertalot/actions/sub_actions/load_target_action.py
alertalot/actions/sub_actions/load_template_action.py
alertalot/actions/sub_actions/load_variables_file_action.py
alertalot/entities/__init__.py
alertalot/entities/aws_ec2_entity.py
alertalot/entities/aws_entity_factory.py
alertalot/entities/aws_generic_entity.py
alertalot/entities/base_aws_entity.py
alertalot/exception/__init__.py
alertalot/exception/invalid_template_exception.py
alertalot/generic/__init__.py
alertalot/generic/args_object.py
alertalot/generic/file_loader.py
alertalot/generic/input_parser.py
alertalot/generic/output.py
alertalot/generic/target_type.py
alertalot/generic/variables.py
alertalot/validation/__init__.py
alertalot/validation/alarms_config_validator.py
alertalot/validation/aws_alarm_validator.py
alertalot-0.2.0.dist-info/licenses/LICENSE.txt
alertalot-0.2.0.dist-info/METADATA
alertalot-0.2.0.dist-info/WHEEL
alertalot-0.2.0.dist-info/entry_points.txt
alertalot-0.2.0.dist-info/top_level.txt
alertalot-0.2.0.dist-info/RECORD
