Metadata-Version: 2.4
Name: alertalot
Version: 0.2.0
Summary: Python library for creating AWS CloudWatch alerts automatically based on predefined configurations
Author-email: Alexey Puchkov <alexey.pkv@gmail.com>
License-Expression: MIT
Project-URL: Homepage, https://github.com/Oktopost/Alertalot
Classifier: Programming Language :: Python :: 3.10
Classifier: Development Status :: 4 - Beta
Classifier: Intended Audience :: Developers
Classifier: Operating System :: OS Independent
Classifier: Topic :: Software Development :: Libraries
Classifier: Topic :: System :: Monitoring
Requires-Python: >=3.10
License-File: LICENSE.txt
Requires-Dist: boto3>=1.37.0
Requires-Dist: pyyaml>=6.0.2
Requires-Dist: pytimeparse>=1.1.8
Requires-Dist: jsonschema>=4.23.0
Requires-Dist: rich>=14.0.0
Provides-Extra: dev
Requires-Dist: pytest>=8.3.4; extra == "dev"
Requires-Dist: pytest-cov>=6.0.0; extra == "dev"
Requires-Dist: pylint>=3.3.4; extra == "dev"
Dynamic: license-file
